bjx_meit/__init__.py
bjx_meit/metrics.py
bjx_meit/models.py
bjx_meit/preprocessing.py
bjx_meit/utils.py
bjx_meit1/__init__.py
bjx_meit1/metrics.py
bjx_meit1/models.py
bjx_meit1/preprocessing.py
bjx_meit1/utils.py
bx_meit/__init__.py
bx_meit/metrics.py
bx_meit/models.py
bx_meit/preprocessing.py
bx_meit/utils.py
meit/__init__.py
meit/metrics.py
meit/models.py
meit/preprocessing.py
meit/utils.py
tests/__init__.py
tests/test_metrics.py
tests/test_models.py
tests/test_preprocessing.py
bjx_meit1-0.1.1.dist-info/METADATA
bjx_meit1-0.1.1.dist-info/WHEEL
bjx_meit1-0.1.1.dist-info/top_level.txt
bjx_meit1-0.1.1.dist-info/RECORD
