Metadata-Version: 2.1
Name: bjx-meit1
Version: 0.1.1
Summary: A toolkit for medical image analysis, including preprocessing, models, and metrics.
Home-page: https://github.com/EmekaIwuagwu/bjx_meit1
Author: Emeka Iwuagwu
Author-email: e.iwuagwu@hotmail.com
Classifier: Programming Language :: Python :: 3
Classifier: License :: OSI Approved :: MIT License
Classifier: Operating System :: OS Independent
Requires-Dist: numpy
Requires-Dist: pandas
Requires-Dist: scikit-learn
Requires-Dist: opencv-python
Requires-Dist: tensorflow
Requires-Dist: keras
Requires-Dist: matplotlib
